kitt/__init__.py
kitt/__version__.py
kitt/client.py
kitt/config.py
kitt/crypto.py
kitt/images.py
kitt/kitt.py
kitt/logger.py
kitt/plugins.py
kitt/vault.py
kitt/static/Dockerfile.j2
kitt/static/default.toml
kitt/static/plugins/copy.j2
kitt/static/plugins/download.j2
kitt/static/plugins/git.j2
kitt/static/plugins/pip.j2
kitt/static/plugins/shell.j2
kitt/static/plugins/zsh.j2
kitt_shell-0.8.6.dist-info/LICENCE.md
kitt_shell-0.8.6.dist-info/METADATA
kitt_shell-0.8.6.dist-info/WHEEL
kitt_shell-0.8.6.dist-info/entry_points.txt
kitt_shell-0.8.6.dist-info/top_level.txt
kitt_shell-0.8.6.dist-info/RECORD
