Metadata-Version: 2.1
Name: kitt-shell
Version: 0.8.6
Summary: A portable containerized shell
Home-page: https://github.com/senges/kitt
Author: Charles SENGES
Author-email: charles.senges.io+github@protonmail.com
Project-URL: Bug Tracker, https://github.com/senges/kitt/issues
Classifier: Programming Language :: Python :: 3
Classifier: License :: OSI Approved :: MIT License
Classifier: Operating System :: OS Independent
Requires-Python: >=3.6
License-File: LICENCE.md
Requires-Dist: docker
Requires-Dist: dockerpty
Requires-Dist: rich
Requires-Dist: toml
Requires-Dist: click
Requires-Dist: fs
Requires-Dist: jinja2
